MANIFEST.in
README.rst
setup.py
docs/HISTORY.txt
docs/LICENSE.GPL
docs/LICENSE.txt
supervisor_haproxy/__init__.py
supervisor_haproxy/command.py
supervisor_haproxy/event_listener.py
supervisor_haproxy/exceptions.py
supervisor_haproxy/haproxy_control.py
supervisor_haproxy.egg-info/PKG-INFO
supervisor_haproxy.egg-info/SOURCES.txt
supervisor_haproxy.egg-info/dependency_links.txt
supervisor_haproxy.egg-info/entry_points.txt
supervisor_haproxy.egg-info/not-zip-safe
supervisor_haproxy.egg-info/requires.txt
supervisor_haproxy.egg-info/top_level.txt
supervisor_haproxy/tests/__init__.py
supervisor_haproxy/tests/haproxy_control.py
supervisor_haproxy/tests/test_haproxy_control.py
supervisor_haproxy/tests/test_haproxy_event_listener.py