Metadata-Version: 1.0
Name: supervisor-haproxy
Version: 1.1.0
Summary: supervisor eventlistener for notifying haproxy
Home-page: https://github.com/4teamwork/supervisor-haproxy
Author: 4teamwork AG
Author-email: mailto:info@4teamwork.ch
License: GPL2
Platform: UNKNOWN
